cvebased/__init__.py
cvebased/common.py
cvebased/repo.py
cvebased-0.1.7.dist-info/WHEEL
cvebased-0.1.7.dist-info/METADATA
cvebased-0.1.7.dist-info/RECORD
